odoo9_addon_account_analytic_no_lines-9.0.1.0.0.99.dev7-py3.8-nspkg.pth
odoo_addons/account_analytic_no_lines/README.rst
odoo_addons/account_analytic_no_lines/__init__.py
odoo_addons/account_analytic_no_lines/__openerp__.py
odoo_addons/account_analytic_no_lines/data/data_account_analytic_group.xml
odoo_addons/account_analytic_no_lines/i18n/account_analytic_no_lines.pot
odoo_addons/account_analytic_no_lines/i18n/ca.po
odoo_addons/account_analytic_no_lines/i18n/es.po
odoo_addons/account_analytic_no_lines/models/__init__.py
odoo_addons/account_analytic_no_lines/models/account_invoice.py
odoo_addons/account_analytic_no_lines/models/account_move_line.py
odoo_addons/account_analytic_no_lines/static/description/icon.png
odoo_addons/account_analytic_no_lines/tests/__init__.py
odoo_addons/account_analytic_no_lines/tests/test_account_analytic_no_lines.py
odoo_addons/account_analytic_no_lines/views/account_analytic.xml
odoo_addons/account_analytic_no_lines/views/account_analytic_account.xml
odoo9_addon_account_analytic_no_lines-9.0.1.0.0.99.dev7.dist-info/METADATA
odoo9_addon_account_analytic_no_lines-9.0.1.0.0.99.dev7.dist-info/WHEEL
odoo9_addon_account_analytic_no_lines-9.0.1.0.0.99.dev7.dist-info/namespace_packages.txt
odoo9_addon_account_analytic_no_lines-9.0.1.0.0.99.dev7.dist-info/top_level.txt
odoo9_addon_account_analytic_no_lines-9.0.1.0.0.99.dev7.dist-info/RECORD
