Metadata-Version: 2.1
Name: odoo9-addon-account-analytic-no-lines
Version: 9.0.1.0.0.99.dev7
Summary: This module hides analytics lines from accounting menus and disable their generation from an invoice or a move line.
Home-page: https://acsone.eu/
Author: ACSONE SA/NV,Odoo Community Association (OCA)
Author-email: support@odoo-community.org
License: AGPL-3
Platform: UNKNOWN
Classifier: Programming Language :: Python
Classifier: Framework :: Odoo
Classifier: Framework :: Odoo :: 9.0
Classifier: License :: OSI Approved :: GNU Affero General Public License v3
Requires-Python: ~=2.7
Requires-Dist: odoo (<9.1a,>=9.0a)
